yasc_script_runner/__init__.py
yasc_script_runner/__main__.py
yasc_script_runner/main.py
yasc_script_runner/script_server.py
yasc_script_runner/script_service.py
yasc_script_runner/watchdog_handler.py
yasc_script_runner/yasc_client.py
yasc_script_runner/proto/__init__.py
yasc_script_runner/proto/script_pb2.py
yasc_script_runner/proto/script_pb2.pyi
yasc_script_runner/proto/script_pb2_grpc.py
yasc_script_runner/proto/yasc_pb2.py
yasc_script_runner/proto/yasc_pb2.pyi
yasc_script_runner/proto/yasc_pb2_grpc.py
yasc_script_runner-1.0.1.dist-info/METADATA
yasc_script_runner-1.0.1.dist-info/WHEEL
yasc_script_runner-1.0.1.dist-info/entry_points.txt
yasc_script_runner-1.0.1.dist-info/licenses/LICENSE
yasc_script_runner-1.0.1.dist-info/RECORD
